ecdysis/__init__.py
ecdysis/ecdysis.py
ecdysis-0.3.0.dist-info/entry_points.txt
ecdysis-0.3.0.dist-info/LICENSE
ecdysis-0.3.0.dist-info/WHEEL
ecdysis-0.3.0.dist-info/METADATA
ecdysis-0.3.0.dist-info/RECORD
