Metadata-Version: 2.1
Name: ecdysis
Version: 0.3.0
Summary: Interface to pyprocessmacro
Home-page: https://github.com/datagazing/ecdysis
Author: Brendan Strejcek
Author-email: brendan@datagazing.com
Requires-Python: >=3.7
Classifier: License :: OSI Approved :: MIT License
Requires-Dist: numpy
Requires-Dist: pandas
Requires-Dist: pyprocessmacro
Requires-Dist: optini
Requires-Dist: pandect
